{
  "display": {
    "icon": {
      "item": "minecraft:wooden_pickaxe"
    },
    "title": {
      "translate": "advancements.xeno_early_start.wooden_pickaxe.title"
    },
    "description": {
      "translate": "advancements.xeno_early_start.wooden_pickaxe.description"
    },
    "frame": "task",
    "show_toast": true,
    "announce_to_chat": true,
    "hidden": true
  },
  "parent": "xeno_early_start:knapping",
  "criteria": {
    "wooden_pickaxe": {
      "trigger": "minecraft:inventory_changed",
      "conditions": {
        "items": [
          {
            "items": [
              "minecraft:wooden_pickaxe"
            ]
          }
        ]
      }
    }
  }
}